cordra_mcp/__init__.py
cordra_mcp/client.py
cordra_mcp/config.py
cordra_mcp/server.py
cordra_mcp-1.4.0.dist-info/METADATA
cordra_mcp-1.4.0.dist-info/WHEEL
cordra_mcp-1.4.0.dist-info/entry_points.txt
cordra_mcp-1.4.0.dist-info/licenses/LICENSE
cordra_mcp-1.4.0.dist-info/RECORD
