Metadata-Version: 2.4
Name: cordra-mcp
Version: 1.4.0
Summary: MCP server for Cordra digital object repository
Project-URL: Homepage, https://github.com/dnlbauer/cordra-mcp
Project-URL: Repository, https://github.com/dnlbauer/cordra-mcp
Author-email: Daniel Bauer <github@dbauer.me>
License: MIT
License-File: LICENSE
Keywords: MCP,agent-coding,ai,cordra,digital-repository,model-context-protocol
Classifier: Intended Audience :: Developers
Classifier: Intended Audience :: System Administrators
Classifier: License :: OSI Approved :: MIT License
Classifier: Operating System :: OS Independent
Classifier: Programming Language :: Python :: 3
Classifier: Topic :: Database :: Database Engines/Servers
Classifier: Topic :: Scientific/Engineering :: Artificial Intelligence
Classifier: Typing :: Typed
Requires-Python: >=3.11
Requires-Dist: mcp[cli]>=1.2.0
Requires-Dist: pydantic-settings>=2.0.0
Requires-Dist: pydantic>=2.0.0
Requires-Dist: requests>=2.25.0
Provides-Extra: dev
Requires-Dist: loguru>=0.7.0; extra == 'dev'
Requires-Dist: mypy>=1.6.0; extra == 'dev'
Requires-Dist: pytest-asyncio>=0.21.0; extra == 'dev'
Requires-Dist: pytest-cov>=4.1.0; extra == 'dev'
Requires-Dist: pytest>=7.4.0; extra == 'dev'
Requires-Dist: ruff>=0.1.0; extra == 'dev'
Provides-Extra: production
